id_generator/__init__.py
id_generator/generator.py
lms_id_generator-0.0.5.dist-info/METADATA
lms_id_generator-0.0.5.dist-info/WHEEL
lms_id_generator-0.0.5.dist-info/top_level.txt
lms_id_generator-0.0.5.dist-info/zip-safe
lms_id_generator-0.0.5.dist-info/RECORD
